simple_bgpfuzz_rpc/__init__.py
simple_bgpfuzz_rpc/rpc.py
simple_bgpfuzz_rpc-0.2.dist-info/LICENSE
simple_bgpfuzz_rpc-0.2.dist-info/METADATA
simple_bgpfuzz_rpc-0.2.dist-info/WHEEL
simple_bgpfuzz_rpc-0.2.dist-info/top_level.txt
simple_bgpfuzz_rpc-0.2.dist-info/RECORD
