Metadata-Version: 2.1
Name: simple-bgpfuzz-rpc
Version: 0.2
Summary: A bgp rpc monitor for boofuzz
Author: P.Dashevskyi
Author-email: 
Classifier: Programming Language :: Python :: 3
Classifier: License :: OSI Approved :: MIT License
Classifier: Operating System :: OS Independent
License-File: LICENSE
Requires-Dist: Boofuzz >=0.4.1
